odoo/addons/partner_contact_association/LICENSE
odoo/addons/partner_contact_association/README.rst
odoo/addons/partner_contact_association/__init__.py
odoo/addons/partner_contact_association/__manifest__.py
odoo/addons/partner_contact_association/demo/association_demo.xml
odoo/addons/partner_contact_association/i18n/de_CH.po
odoo/addons/partner_contact_association/images/screen.png
odoo/addons/partner_contact_association/models/__init__.py
odoo/addons/partner_contact_association/models/association.py
odoo/addons/partner_contact_association/models/res_partner.py
odoo/addons/partner_contact_association/readme/CONTRIBUTORS.md
odoo/addons/partner_contact_association/readme/DESCRIPTION.md
odoo/addons/partner_contact_association/readme/USAGE.md
odoo/addons/partner_contact_association/security/ir.model.access.csv
odoo/addons/partner_contact_association/static/description/icon.png
odoo/addons/partner_contact_association/static/description/index.html
odoo/addons/partner_contact_association/tests/TEST_INSTRUCTIONS.rst
odoo/addons/partner_contact_association/views/association.xml
odoo/addons/partner_contact_association/views/res_partner.xml
odoo_addon_partner_contact_association-18.0.1.0.0.dist-info/METADATA
odoo_addon_partner_contact_association-18.0.1.0.0.dist-info/WHEEL
odoo_addon_partner_contact_association-18.0.1.0.0.dist-info/top_level.txt
odoo_addon_partner_contact_association-18.0.1.0.0.dist-info/RECORD
